odoo/addons/storage_backend_sftp/README.rst
odoo/addons/storage_backend_sftp/__init__.py
odoo/addons/storage_backend_sftp/__manifest__.py
odoo/addons/storage_backend_sftp/components/__init__.py
odoo/addons/storage_backend_sftp/components/sftp_adapter.py
odoo/addons/storage_backend_sftp/i18n/storage_backend_sftp.pot
odoo/addons/storage_backend_sftp/models/__init__.py
odoo/addons/storage_backend_sftp/models/storage_backend.py
odoo/addons/storage_backend_sftp/static/description/icon.png
odoo/addons/storage_backend_sftp/tests/__init__.py
odoo/addons/storage_backend_sftp/tests/test_sftp.py
odoo/addons/storage_backend_sftp/views/backend_storage_view.xml
odoo13_addon_storage_backend_sftp-13.0.1.4.1.dist-info/METADATA
odoo13_addon_storage_backend_sftp-13.0.1.4.1.dist-info/WHEEL
odoo13_addon_storage_backend_sftp-13.0.1.4.1.dist-info/top_level.txt
odoo13_addon_storage_backend_sftp-13.0.1.4.1.dist-info/RECORD
